verdict/__init__.py
verdict/agents.py
verdict/artifacts.py
verdict/cli.py
verdict/config.py
verdict/context.py
verdict/llm_providers.py
verdict/pipeline.py
verdict/schemas/execution.json
verdict/schemas/verdict.json
verdict/storage.py
verdict/templates/decision.json.j2
verdict/templates/execution_agent.j2
verdict/templates/state.json.j2
verdict/templates/todo.md.j2
verdict/templates/verdict_agent.j2
verdict/validator.py
verdict_ai-0.2.4.dist-info/METADATA
verdict_ai-0.2.4.dist-info/WHEEL
verdict_ai-0.2.4.dist-info/entry_points.txt
verdict_ai-0.2.4.dist-info/licenses/LICENSE
verdict_ai-0.2.4.dist-info/RECORD
