Metadata-Version: 2.4
Name: verdict-ai
Version: 0.2.4
Summary: AI-powered meta-decision system with dual constrained agents
License: MIT
License-File: LICENSE
Keywords: ai,decision-making,cli,anthropic,claude,openai,gemini,llm
Author: 1psychoQAQ
Author-email: noreply@github.com
Requires-Python: >=3.10
Classifier: Development Status :: 4 - Beta
Classifier: Intended Audience :: Developers
Classifier: License :: OSI Approved :: MIT License
Classifier: Programming Language :: Python :: 3
Classifier: Programming Language :: Python :: 3.10
Classifier: Programming Language :: Python :: 3.11
Classifier: Programming Language :: Python :: 3.12
Classifier: Programming Language :: Python :: 3.13
Classifier: Topic :: Software Development :: Libraries :: Python Modules
Classifier: Topic :: Utilities
Provides-Extra: all
Provides-Extra: gemini
Provides-Extra: openai
Requires-Dist: anthropic (>=0.75.0,<0.76.0)
Requires-Dist: click (>=8.3.1,<9.0.0)
Requires-Dist: google-genai (>=0.2.0,<1.0.0) ; extra == "all"
Requires-Dist: google-genai (>=0.2.0,<1.0.0) ; extra == "gemini"
Requires-Dist: jinja2 (>=3.1.6,<4.0.0)
Requires-Dist: jsonschema (>=4.25.1,<5.0.0)
Requires-Dist: openai (>=1.59.8,<2.0.0) ; extra == "all"
Requires-Dist: openai (>=1.59.8,<2.0.0) ; extra == "openai"
Requires-Dist: pyyaml (>=6.0.3,<7.0.0)
Requires-Dist: rich (>=14.2.0,<15.0.0)
Project-URL: Documentation, https://github.com/1psychoQAQ/verdict#readme
Project-URL: Homepage, https://github.com/1psychoQAQ/verdict
Project-URL: Issues, https://github.com/1psychoQAQ/verdict/issues
Project-URL: Repository, https://github.com/1psychoQAQ/verdict
